README.rst
setup.cfg
setup.py
papa1024/__init__.py
papa1024/board.py
papa1024/index.py
papa1024/post.py
papa1024.egg-info/PKG-INFO
papa1024.egg-info/SOURCES.txt
papa1024.egg-info/dependency_links.txt
papa1024.egg-info/requires.txt
papa1024.egg-info/top_level.txt