Metadata-Version: 1.1
Name: papa1024
Version: 1.0.6
Summary: papa1024 is the web crawler application of the 1024 forum.
Home-page: https://github.com/liuziyuan/papa1024
Author: liuziyuan
Author-email: liuziyuan.room@gmail.com
License: MIT
Platform: UNKNOWN
Classifier: Development Status :: 5 - Production/Stable
Classifier: Intended Audience :: Developers
Classifier: Natural Language :: English
Classifier: License :: OSI Approved :: MIT License
Classifier: Programming Language :: Python
Classifier: Programming Language :: Python :: 3
Classifier: Programming Language :: Python :: 3.5
Classifier: Programming Language :: Python :: 3.6
